{
  "inspector-resize-container-border": "$inspector-border",
  "black-20": "$black:alpha(0.20)",
  "license-window-error-text": "#E01F1F",
  "canvas-ruler-occupied": "#CCE9FF",
  "tiled-image-view-background": "$white-80",
  "black-50": "$black:alpha(0.50)",
  "canvas-layer-selection": "rgb(170, 170, 170)",
  "inspector-slider-right-track": "$black-10",
  "stepper-button-pressed-dark": "#999999",
  "canvas-artboard-title": "srgb(146, 146, 146)",
  "mscollectionview-row-1": "#EEEEEE",
  "black-25": "$black:alpha(0.25)",
  "window-badge-library-changes": "#B620E0",
  "inspector-slider-knob-dark": "#8A8E93",
  "layer-list-default-divider-dark": "#575859",
  "black-80": "$black:alpha(0.80)",
  "inspector-section-background": "#EDEDED",
  "window-badge-unfocused-pill": "srgba(109,114,120, 0.5)",
  "assistant-selection-color": "$default-accent",
  "inspector-style-preview-button-overlay-highlight-dark": "$white-15",
  "color-picker-checkerboard-border": "@clearColor",
  "documents-window-local-button-background-dark": "$white-25",
  "text-table-contrast": "@lightGrayColor",
  "color-picker-assets-no-content-placeholder-color-dark": "$white-25",
  "white-10": "$white:alpha(0.10)",
  "inspector-slider-knob-border-dark": "$black-15",
  "canvas-ruler-lock-dark": "#808080",
  "layer-list-text-hidden": "$black:alpha(0.5)",
  "inspector-resize-preview-fill": "$inspector-resize-preview-border:alpha(0.7)",
  "white-40": "$white:alpha(0.40)",
  "layer-list-filter-bar-border-dark": "#434445",
  "inspector-alignment-strut-graphite-active-dark": "$white-90",
  "popover-window-outline-dark": "$white:alpha(0.3)",
  "layer-list-filter-token-background-inactive": "$black-10",
  "documents-window-thumbnail-border": "$white",
  "mscollectionview-row-2": "#E7E7E7",
  "inspector-icon": "@secondaryLabelColor",
  "white-15": "$white:alpha(0.15)",
  "inspector-graphite-accent-dark": "$white-90",
  "inspector-resize-root-border": "$inspector-border",
  "documents-window-banner-border": "#EFD17A",
  "cloud-intro-button-background": "$default-accent",
  "inspector-button-drop-shadow-dark": "@clearColor",
  "text-table-row-background": "$white-95p",
  "documents-window-widget-pressed": "$black-10",
  "tungsten": "#6D7278",
  "components-search-result-highlight-underline-dark": "rgba(247,181,0,0.5)",
  "layer-list-artboard-border": "$layer-list-default-divider",
  "documents-window-vertical-divider-dark": "$black",
  "layer-list-filter-bar-border": "$layer-list-default-divider",
  "inspector-separator-dark": "$white-10",
  "mscollectionview-column-separator": "#D3D3D3",
  "overlay-button-background": "$black:alpha(0.6)",
  "layer-list-default-divider": "#dadadb",
  "layer-list-filter-token-background-dark-inactive": "$white-10",
  "stepper-button-pressed": "$black-20",
  "canvas-artboard-title-dark": "srgb(146, 146, 146)",
  "inspector-alignment-strut-graphite-active": "$black-70",
  "canvas-page-background-dark": "#131415",
  "black-17": "$black:alpha(0.17)",
  "inspector-section-header-text": "$black-50",
  "assistant-capsule-yellow-dark": "rgba(247,181,0,0.9)",
  "background-ui-color": "#F2F2F2",
  "inspector-push-button-background": "$inspector-button-background",
  "inspector-override-icon-tint": "$black:alpha(0.5)",
  "layer-list-symbol-override-selection": "$default-accent:alpha(0.15)",
  "tableviewcell-button-background": "$default-accent",
  "header-background": "$white-50",
  "canvas-background-dark": "#1D1E1F",
  "inspector-slider-right-track-dark": "$inspector-label-background",
  "hover-button-normal": "#888888",
  "inspector-alignment-background-dark": "#454647",
  "layer-list-tab-button-dark": "@tintColorNormalDark",
  "layer-list-filter-token-background-selected-inactive": "$black-20",
  "inspector-artboard-preset-header-color": "$background-ui-color",
  "layer-list-tab-button": "@tintColorNormal",
  "inspector-label-background": "$white",
  "color-picker-color-model-picker-background-color-active": "$black-20",
  "color-picker-color-mode-picker-accented-icon-graphite-dark": "$inspector-graphite-accent-icon-dark",
  "layer-list-filter-bar-background-dark": "$layer-list-background",
  "layer-list-symbol-override-selection-dark-inactive": "$white-5",
  "inspector-slider-knob": "$white",
  "layer-list-artboard-border-selected": "$white-10",
  "canvas-symbol-title-dark": "#CC63E9",
  "white": "#FFFFFF",
  "assistant-capsule-green": "rgba(109,212,0,0.5)",
  "canvas-ruler-background-dark": "#000000",
  "hover-button-hover": "#555555",
  "popover-window-background": "$white",
  "canvas-ruler-text": "rgba(0, 0, 0, 0.85)",
  "layer-list-icon-tint-selected-dark-inactive": "@tintColorNormalDark",
  "canvas-ruler-line": "#D0D0D0",
  "asset-picker-image-item-background-dark": "$white",
  "color-picker-checkerboard-background": "$white",
  "white-62p": "rgba(158, 158, 158, 1.0)",
  "inspector-artboard-tableview-background-color-dark": "#2E2F30",
  "layer-list-icon-tint-pressed": "$default-accent",
  "inspector-separator": "$black-10",
  "documents-window-thumbnail-bg-dark": "$black-70",
  "header-background-dark": "$black-20",
  "stepper-button-separator-dark": "#8C8C8C",
  "white-18p": "rgba(46, 46, 46, 1.0)",
  "inspector-border-dark": "$white-10",
  "black-10": "$black:alpha(0.10)",
  "layer-list-selection-dark-inactive": "$white-10",
  "inspector-background": "$background-ui-color",
  "documents-window-local-button-background-highlight-dark": "$white:alpha(0.35)",
  "inspector-resize-root-fill": "$black:alpha(0.02)",
  "layer-list-filter-token-background": "$default-accent:alpha(0.15)",
  "red": "#F00",
  "inspector-inline-label-text": "@secondaryLabelColor",
  "documents-window-local-button-inner-shadow": "$white:alpha(0.35)",
  "color-picker-checkerboard-background-dark": "#2b2d30",
  "layer-list-icon-tint-shared-dark": "#C44CE6",
  "black-5": "$black:alpha(0.05)",
  "preferences-window-error-text": "#EF001C",
  "preferences-asset-library-header-background": "@windowBackgroundColor",
  "inspector-slider-knob-border": "$black-15",
  "documents-window-thumbnail-bg": "#F7F7F7",
  "window-badge-multiple-notifications": "#E02020",
  "black-15": "$black:alpha(0.15)",
  "layer-list-background-dark": "$background-ui-color-dark",
  "color-picker-color-controls-border-dark": "$white-25",
  "black-70": "$black:alpha(0.70)",
  "canvas-override-selection-back": "$white",
  "color-picker-color-mode-picker-accented-icon-graphite": "$black-80",
  "layer-list-icon-tint-shared": "#B620E0",
  "components-search-result-highlight-background-dark": "rgba(247,181,0,0.15)",
  "documents-window-banner-background": "#FBE199",
  "canvas-ruler-text-dark": "rgba(255, 255, 255, 0.85)",
  "color-picker-separator": "#E5E5E5",
  "documents-window-text-selection": "$default-accent",
  "documents-window-banner-text-dark": "#FBE199",
  "inspector-label-background-dark": "$white-27p",
  "inspector-label-text": "@labelColor",
  "inspector-push-button-background-dark": "#5d5f61",
  "layer-list-symbol-override-selection-inactive": "$black-5",
  "text-table-row-background-dark": "$white-5p",
  "documents-window-divider-dark": "$white",
  "documents-window-status-icon-dark": "$white-50",
  "inspector-button-drop-shadow": "$black:alpha(0.07)",
  "canvas-ruler-line-dark": "#575B60",
  "white-30": "$white:alpha(0.30)",
  "color-picker-color-controls-border": "$black-25",
  "inspector-border": "$black-17",
  "inspector-style-preview-button-overlay-highlight": "$black-10",
  "inspector-section-header-text-dark": "$white-50",
  "mscollectionview-row-1-dark": "#323335",
  "documents-window-status-icon": "$black:alpha(0.40)",
  "inspector-alignment-strut-disabled": "$black-10",
  "cloud-popover-button-tint-dark": "$white-50",
  "component-pane-group-preview-background-dark": "$white:alpha(0.16)",
  "layer-list-filter-token-background-selected-dark": "$default-accent",
  "inspector-graphite-accent": "$black-70",
  "canvas-ruler-lock": "#7F7F7F",
  "inspector-graphite-accent-icon": "$black-70",
  "components-filter-bar-background": "@controlColor",
  "window-badge-library-updates": "#6236FF",
  "color-picker-checkerboard-foreground": "$white-77p",
  "white-90": "$white:alpha(0.90)",
  "layer-list-selection": "$default-accent",
  "split-view-divider-dark": "$black",
  "canvas-slice-outline": "#CCCCCC",
  "documents-window-status-icon-selected": "$white",
  "window-badge-fonts-missing": "#3DC1A3",
  "mscollectionview-column-separator-dark": "#0B0B0B",
  "tiled-image-view-background-dark": "$black-80",
  "documents-window-banner-button-dark": "#FBE199",
  "inspector-section-separator": "#C6C6C6",
  "cloud-popover-cancel-button-tint-pressed": "$black:alpha(0.75)",
  "white-95": "$white:alpha(0.95)",
  "components-kind-bar-background": "@controlColor",
  "color-picker-marker-fill": "$white",
  "inspector-background-dark": "$background-ui-color-dark",
  "canvas-pixel-line": "rgba(242, 242, 242, 0.3)",
  "document-item-overlay-dark": "rgba(82,82,82,0.40)",
  "layer-list-filter-token-title-dark": "@tintColorIntenseDark",
  "layer-list-icon-tint-selected-inactive": "$layer-list-icon-tint",
  "components-filter-bar-background-dark": "$layer-list-light-background-dark",
  "documents-window-seperator": "$black-10",
  "white-77p": "rgba(196, 196, 196, 1.0)",
  "asset-picker-image-item-background": "$black-5",
  "components-kind-bar-background-dark": "$layer-list-light-background-dark",
  "layer-list-filter-token-background-selected-dark-inactive": "$white-20",
  "stepper-button-background-dark": "#808080",
  "canvas-ruler-text-background": "rgba(255,255,255,0.80)",
  "color-picker-asset-border-dark": "$white-20",
  "documents-window-seperator-dark": "$white-10",
  "popover-window-background-dark": "#282828:alpha(0.93)",
  "skBlue-50": "$skBlue:alpha(0.50)",
  "asset-picker-item-border-color-dark": "$white-10",
  "layer-list-icon-tint-selected": "$white",
  "inspector-artboard-preset-header-color-dark": "#454647",
  "layer-list-light-background-dark": "#454647",
  "color-picker-assets-no-content-placeholder-color": "$black-25",
  "documents-window-local-button-background": "$white-50",
  "layer-list-icon-tint": "@tintColorNormal",
  "layer-list-symbol-override-icon-tint": "$skBlue",
  "layer-list-filter-token-background-selected": "$default-accent",
  "color-picker-color-model-picker-background-color-dark": "$white-10",
  "stepper-button-background": "$white",
  "color-picker-asset-border": "rgba(0,0,0,0.15)",
  "inspector-accented-background-icon": "$white",
  "cloud-popover-cancel-button-tint-dark": "$white-50",
  "canvas-page-background": "#F9F9F9",
  "inspector-button-background": "$inspector-label-background",
  "assistant-capsule-grey": "rgba(180,180,180,0.9)",
  "documents-window-banner-button": "#946C00",
  "layer-list-filter-token-title": "@tintColorIntense",
  "color-picker-modified-asset-indicator-border-dark": "#27282B",
  "assistant-capsule-red": "rgba(224,32,32,0.9)",
  "layer-list-icon-tint-pressed-selected": "$white:alpha(0.75)",
  "layer-list-split-view-divider-dark": "$layer-list-default-divider-dark",
  "documents-window-local-button-inner-shadow-dark": "$white:alpha(0.12)",
  "canvas-measurement-label-background": "rgba(0,0,0,0.30)",
  "skBlue": "#0091FF",
  "black": "#000000",
  "layer-list-background": "$background-ui-color",
  "stepper-button-arrow": "$black-50",
  "background-ui-color-dark": "#2E2F30",
  "inspector-label-text-dark": "$white-85",
  "color-picker-checkerboard-foreground-dark": "$white-27p",
  "split-view-divider": "#D0D0D0",
  "canvas-layer-highlight": "$default-accent",
  "canvas-background": "$white",
  "documents-window-banner-border-dark": "#5E4F23",
  "assistant-capsule-red-dark": "rgba(224,32,32,0.9)",
  "documents-window-local-button-border": "$black-15",
  "inspector-alignment-background": "#fafafa",
  "inspector-resize-handle-fill-dark": "srgba(5,5,5,1)",
  "inspector-inline-label-text-dark": "$white-62p",
  "documents-window-banner-background-dark": "#4B3F1D",
  "preferences-account-box-background-dark": "$white:alpha(0.03)",
  "documents-window-thumbnail-border-dark": "#36383A",
  "white-95p": "rgba(242, 242, 242, 1.0)",
  "layer-list-icon-tint-dark": "@tintColorNormalDark",
  "components-search-result-highlight-background": "rgba(247,181,0,0.25)",
  "documents-window-local-button-second-inner-shadow": "$white:alpha(0.03)",
  "window-badge-text": "#FFFFFF",
  "canvas-override-selection": "$default-accent",
  "inspector-accent": "$default-accent",
  "layer-list-text": "@tintColorIntense",
  "text-table-contrast-dark": "@lightGrayColor",
  "cloud-popover-button-tint": "$black:alpha(0.25)",
  "flow-tint": "$black-25",
  "stepper-button-arrow-dark": "$white",
  "stepper-button-separator": "$black-10",
  "color-picker-color-model-picker-background-color": "$black-10",
  "preferences-asset-library-header-border-dark": "$white-15",
  "layer-list-tab-button-selected": "@tintColorIntense",
  "white-20": "$white:alpha(0.20)",
  "layer-list-light-background": "#FAFAFA",
  "documents-window-divider": "$black",
  "document-item-overlay": "$black-20",
  "default-accent": "@controlAccentColor; $skBlue",
  "inspector-graphite-accent-icon-dark": "$white-90",
  "white-50": "$white:alpha(0.50)",
  "layer-list-filter-bar-background": "$white",
  "documents-window-vertical-divider": "#B2B2B2",
  "component-pane-group-preview-background": "$black:alpha(0.08)",
  "color-picker-checkerboard-border-dark": "$white-10",
  "inspector-override-config-header": "$black:alpha(0.04)",
  "layer-list-artboard-border-dark": "$layer-list-default-divider-dark",
  "white-25": "$white:alpha(0.25)",
  "inspector-resize-preview-border": "rgba(109,212,0,1.0)",
  "assistant-capsule-grey-dark": "rgba(150,150,150,0.9)",
  "white-80": "$white:alpha(0.80)",
  "canvas-symbol-title": "srgba(182, 32, 224, 0.7)",
  "color-picker-color-controls-knob-border": "$black-25",
  "inspector-resize-handle-border": "rgba(182,184,187,1.0)",
  "asset-picker-item-border-color": "$black-10",
  "color-picker-modified-asset-indicator-border": "$white",
  "tungsten-80": "rgba(109,114,120,0.80)",
  "canvas-flow-arrow": "rgb(245, 152, 0, 1)",
  "window-badge-plugin-updates": "#FA6400",
  "cloud-popover-cancel-button-tint": "$black-50",
  "mscollectionview-row-2-dark": "#28292B",
  "documents-window-local-button-background-highlight": "$black-5",
  "white-85": "$white:alpha(0.85)",
  "layer-list-filter-token-title-selected": "$white",
  "assistant-capsule-green-dark": "rgba(109,212,0,0.5)",
  "white-5p": "#0D0D0D",
  "flow-tint-dark": "$white-50",
  "component-pane-text-item-missing-font-background": "#F8C332:alpha(0.5)",
  "inspector-override-config-header-dark": "$white:alpha(0.07)",
  "preferences-asset-library-header-border": "$black-10",
  "white-5": "$white:alpha(0.05)",
  "inspector-label-border": "$inspector-border",
  "inspector-resize-container-fill": "$inspector-button-background",
  "layer-list-text-dark": "@tintColorIntenseDark",
  "layer-list-text-hidden-dark": "$white:alpha(0.5)",
  "components-search-result-highlight-underline": "rgba(247,181,0,1)",
  "color-picker-color-model-picker-background-color-active-dark": "$white-20",
  "skBlue-15": "$skBlue:alpha(0.15)",
  "color-picker-frequent-image-background": "$black-5",
  "documents-window-selection": "$default-accent",
  "inspector-override-icon-tint-dark": "$white:alpha(0.5)",
  "assistant-capsule-yellow": "rgba(247,181,0,0.9)",
  "layer-list-filter-token-background-dark": "$default-accent:alpha(0.50)",
  "canvas-ruler-line-occupied": "#7CB6E2",
  "inspector-section-background-dark": "$inspector-background-dark",
  "color-picker-pattern-image-border": "$black-15",
  "layer-list-selection-inactive": "$black-10",
  "preferences-account-box-background": "$black:alpha(0.03)",
  "white-27p": "rgba(69, 69, 69, 1.0)",
  "layer-list-tab-button-selected-dark": "@tintColorIntenseDark",
  "canvas-ruler-background": "$white",
  "color-picker-marker-shadow": "$black-10",
  "inspector-secondary-label-text-highlighted": "$white:alpha(0.8)",
  "color-picker-pattern-image-border-dark": "$white-15",
  "layer-list-split-view-divider": "$layer-list-default-divider",
  "color-picker-label-text": "@tintColorIntense",
  "inspector-alignment-strut-dark": "$white-25",
  "tableviewcell-button-stringcolor": "$white",
  "assistant-capsule-disabled-dark": "rgba(227,227,227,1)",
  "tableviewcell-button-stringcolor-selected": "$default-accent",
  "color-picker-separator-dark": "#505050",
  "inspector-alignment-strut": "$black-25",
  "inspector-resize-handle-fill": "$white",
  "window-badge-trial-message": "#6D7278",
  "inspector-artboard-tableview-background-color": "$white",
  "tableviewcell-button-background-selected": "$white",
  "assistant-capsule-disabled": "rgba(227,227,227,1)",
  "inspector-alignment-strut-disabled-dark": "$white-10",
  "documents-window-banner-text": "#624800",
  "popover-window-outline": "$white:alpha(0.0)",
  "canvas-ruler-text-background-dark": "rgba(33,33,33,0.80)"
}