{"macOS11":{"v72.1":{"theme":{"canvasArtboardTitleColor":{"darkMulticolour":"changed","darkBlue":"changed","darkPurple":"changed","darkPink":"changed","darkRed":"changed","darkOrange":"changed","darkYellow":"changed","darkGreen":"changed","darkGraphite":"changed"},"canvasDarkModeArtboardTitleColor":{"lightMulticolour":"added","lightBlue":"added","lightPurple":"added","lightPink":"added","lightRed":"added","lightOrange":"added","lightYellow":"added","lightGreen":"added","lightGraphite":"added","darkMulticolour":"added","darkBlue":"added","darkPurple":"added","darkPink":"added","darkRed":"added","darkOrange":"added","darkYellow":"added","darkGreen":"added","darkGraphite":"added"},"canvasLightModeArtboardTitleColor":{"lightMulticolour":"added","lightBlue":"added","lightPurple":"added","lightPink":"added","lightRed":"added","lightOrange":"added","lightYellow":"added","lightGreen":"added","lightGraphite":"added","darkMulticolour":"added","darkBlue":"added","darkPurple":"added","darkPink":"added","darkRed":"added","darkOrange":"added","darkYellow":"added","darkGreen":"added","darkGraphite":"added"},"canvasRulerBackgroundColor":{"darkMulticolour":"changed","darkBlue":"changed","darkPurple":"changed","darkPink":"changed","darkRed":"changed","darkOrange":"changed","darkYellow":"changed","darkGreen":"changed","darkGraphite":"changed"},"canvasRulerLineColor":{"darkMulticolour":"changed","darkBlue":"changed","darkPurple":"changed","darkPink":"changed","darkRed":"changed","darkOrange":"changed","darkYellow":"changed","darkGreen":"changed","darkGraphite":"changed"},"colorPickerColorControlsBorder":{"lightMulticolour":"changed","lightBlue":"changed","lightPurple":"changed","lightPink":"changed","lightRed":"changed","lightOrange":"changed","lightYellow":"changed","lightGreen":"changed","lightGraphite":"changed","darkMulticolour":"changed","darkBlue":"changed","darkPurple":"changed","darkPink":"changed","darkRed":"changed","darkOrange":"changed","darkYellow":"changed","darkGreen":"changed","darkGraphite":"changed"},"assetPickerItemBorderColor":{"lightMulticolour":"changed","lightBlue":"changed","lightPurple":"changed","lightPink":"changed","lightRed":"changed","lightOrange":"changed","lightYellow":"changed","lightGreen":"changed","lightGraphite":"changed","darkMulticolour":"changed","darkBlue":"changed","darkPurple":"changed","darkPink":"changed","darkRed":"changed","darkOrange":"changed","darkYellow":"changed","darkGreen":"changed","darkGraphite":"changed"},"assetPickerItemGridHighlightColor":{"lightMulticolour":"changed","lightBlue":"changed","lightPurple":"changed","lightPink":"changed","lightRed":"changed","lightOrange":"changed","lightYellow":"changed","lightGreen":"changed","lightGraphite":"changed","darkMulticolour":"changed","darkBlue":"changed","darkPurple":"changed","darkPink":"changed","darkRed":"changed","darkOrange":"changed","darkYellow":"changed","darkGreen":"changed","darkGraphite":"changed"},"layerListIconSharedTintColor":{"darkMulticolour":"changed","darkBlue":"changed","darkPurple":"changed","darkPink":"changed","darkRed":"changed","darkOrange":"changed","darkYellow":"changed","darkGreen":"changed","darkGraphite":"changed"}},"plist":{"canvas-artboard-title":{"light":{"value":"changed"},"dark":{"value":"changed","interpolation":"changed"}},"canvas-ruler-background":{"dark":{"value":"changed","interpolation":"changed"}},"canvas-ruler-line":{"dark":{"value":"changed","interpolation":"changed"}},"layer-list-icon-tint-shared":{"dark":{"value":"changed","interpolation":"changed"}}},"counters":{"added":36,"changed":99}},"v71":{"plist":{"green":{"light":{"value":"added","interpolation":"added"}},"blue":{"light":{"value":"added","interpolation":"added"}}},"counters":{"added":4}},"v70.2":{"theme":{"componentsColor":{"lightMulticolour":"changed","lightBlue":"changed","lightPurple":"changed","lightPink":"changed","lightRed":"changed","lightOrange":"changed","lightYellow":"changed","lightGreen":"changed","lightGraphite":"changed","darkMulticolour":"changed","darkBlue":"changed","darkPurple":"changed","darkPink":"changed","darkRed":"changed","darkOrange":"changed","darkYellow":"changed","darkGreen":"changed","darkGraphite":"changed"}},"counters":{"changed":18}}},"macOS10":{"v71":{"plist":{"green":{"light":{"value":"added","interpolation":"added"}},"blue":{"light":{"value":"added","interpolation":"added"}}},"counters":{"added":4}},"v70.2":{"theme":{"componentsColor":{"lightBlue":"changed","lightPurple":"changed","lightPink":"changed","lightRed":"changed","lightOrange":"changed","lightYellow":"changed","lightGreen":"changed","lightGraphite":"changed","darkBlue":"changed","darkPurple":"changed","darkPink":"changed","darkRed":"changed","darkOrange":"changed","darkYellow":"changed","darkGreen":"changed","darkGraphite":"changed"}},"counters":{"changed":16}},"v70":{"theme":{"canvasMeasurementLabelBackgroundColor":{"lightBlue":"changed","lightPurple":"changed","lightPink":"changed","lightRed":"changed","lightOrange":"changed","lightYellow":"changed","lightGreen":"changed","lightGraphite":"changed","darkBlue":"changed","darkPurple":"changed","darkPink":"changed","darkRed":"changed","darkOrange":"changed","darkYellow":"changed","darkGreen":"changed","darkGraphite":"changed"},"preferencesAssetLibraryHeaderBackgroundColor":{"lightBlue":"added","lightPurple":"added","lightPink":"added","lightRed":"added","lightOrange":"added","lightYellow":"added","lightGreen":"added","lightGraphite":"added","darkBlue":"added","darkPurple":"added","darkPink":"added","darkRed":"added","darkOrange":"added","darkYellow":"added","darkGreen":"added","darkGraphite":"added"},"preferencesAssetLibraryHeaderBorderColor":{"lightBlue":"added","lightPurple":"added","lightPink":"added","lightRed":"added","lightOrange":"added","lightYellow":"added","lightGreen":"added","lightGraphite":"added","darkBlue":"added","darkPurple":"added","darkPink":"added","darkRed":"added","darkOrange":"added","darkYellow":"added","darkGreen":"added","darkGraphite":"added"},"layerListSymbolOverrideIconTintColor":{"lightBlue":"changed","lightPurple":"changed","lightPink":"changed","lightRed":"changed","lightOrange":"changed","lightYellow":"changed","lightGreen":"changed","lightGraphite":"changed","darkBlue":"changed","darkPurple":"changed","darkPink":"changed","darkRed":"changed","darkOrange":"changed","darkYellow":"changed","darkGreen":"changed","darkGraphite":"changed"},"inspectorButtonDropShadowColor":{"lightBlue":"changed","lightPurple":"changed","lightPink":"changed","lightRed":"changed","lightOrange":"changed","lightYellow":"changed","lightGreen":"changed","lightGraphite":"changed"}},"plist":{"inspector-button-drop-shadow":{"light":{"value":"changed","interpolation":"changed"}},"layer-list-tab-button":{"light":{"value":"changed"}},"split-view-divider":{"light":{"value":"changed","interpolation":"changed"}},"layer-list-icon-tint":{"light":{"value":"changed"}},"canvas-measurement-label-background":{"light":{"value":"changed","interpolation":"changed"}},"default-accent":{"light":{"value":"changed"}},"black-8":{"light":{"value":"added","interpolation":"added"}}},"counters":{"added":34,"changed":49}},"v69":{"theme":{"canvasRulerLockColor":{"lightBlue":"changed","lightPurple":"changed","lightPink":"changed","lightRed":"changed","lightOrange":"changed","lightYellow":"changed","lightGreen":"changed","lightGraphite":"changed","darkBlue":"changed","darkPurple":"changed","darkPink":"changed","darkRed":"changed","darkOrange":"changed","darkYellow":"changed","darkGreen":"changed","darkGraphite":"changed"},"canvasRulerLockPressedColor":{"lightBlue":"added","lightPurple":"added","lightPink":"added","lightRed":"added","lightOrange":"added","lightYellow":"added","lightGreen":"added","lightGraphite":"added","darkBlue":"added","darkPurple":"added","darkPink":"added","darkRed":"added","darkOrange":"added","darkYellow":"added","darkGreen":"added","darkGraphite":"added"},"componentsPanelTextItemMissingFontBackgroundColor":{"lightBlue":"added","lightPurple":"added","lightPink":"added","lightRed":"added","lightOrange":"added","lightYellow":"added","lightGreen":"added","lightGraphite":"added","darkBlue":"added","darkPurple":"added","darkPink":"added","darkRed":"added","darkOrange":"added","darkYellow":"added","darkGreen":"added","darkGraphite":"added"},"componentsColor":{"lightBlue":"added","lightPurple":"added","lightPink":"added","lightRed":"added","lightOrange":"added","lightYellow":"added","lightGreen":"added","lightGraphite":"added","darkBlue":"added","darkPurple":"added","darkPink":"added","darkRed":"added","darkOrange":"added","darkYellow":"added","darkGreen":"added","darkGraphite":"added"},"componentsItemBackgroundColor":{"lightBlue":"added","lightPurple":"added","lightPink":"added","lightRed":"added","lightOrange":"added","lightYellow":"added","lightGreen":"added","lightGraphite":"added","darkBlue":"added","darkPurple":"added","darkPink":"added","darkRed":"added","darkOrange":"added","darkYellow":"added","darkGreen":"added","darkGraphite":"added"},"componentsPanelGroupPreviewBackgroundColor":{"lightBlue":"added","lightPurple":"added","lightPink":"added","lightRed":"added","lightOrange":"added","lightYellow":"added","lightGreen":"added","lightGraphite":"added","darkBlue":"added","darkPurple":"added","darkPink":"added","darkRed":"added","darkOrange":"added","darkYellow":"added","darkGreen":"added","darkGraphite":"added"},"sidebarSeparatorColor":{"lightBlue":"added","lightPurple":"added","lightPink":"added","lightRed":"added","lightOrange":"added","lightYellow":"added","lightGreen":"added","lightGraphite":"added","darkBlue":"added","darkPurple":"added","darkPink":"added","darkRed":"added","darkOrange":"added","darkYellow":"added","darkGreen":"added","darkGraphite":"added"}},"plist":{"canvas-ruler-lock":{"dark":{"value":"changed","interpolation":"changed"},"light":{"value":"changed","interpolation":"changed"}},"canvas-ruler-lock-pressed":{"dark":{"value":"added","interpolation":"added"},"light":{"value":"added","interpolation":"added"}}},"counters":{"added":100,"changed":20}},"v68":{"theme":{"assistantCapsuleRedColor":{"darkBlue":"changed","darkPurple":"changed","darkPink":"changed","darkRed":"changed","darkOrange":"changed","darkYellow":"changed","darkGreen":"changed","darkGraphite":"changed"},"assistantCapsuleYellowColor":{"darkBlue":"changed","darkPurple":"changed","darkPink":"changed","darkRed":"changed","darkOrange":"changed","darkYellow":"changed","darkGreen":"changed","darkGraphite":"changed"},"assistantCapsuleGreenColor":{"lightBlue":"changed","lightPurple":"changed","lightPink":"changed","lightRed":"changed","lightOrange":"changed","lightYellow":"changed","lightGreen":"changed","lightGraphite":"changed"},"documentsWindowBannerBackgroundColor":{"lightBlue":"added","lightPurple":"added","lightPink":"added","lightRed":"added","lightOrange":"added","lightYellow":"added","lightGreen":"added","lightGraphite":"added","darkBlue":"added","darkPurple":"added","darkPink":"added","darkRed":"added","darkOrange":"added","darkYellow":"added","darkGreen":"added","darkGraphite":"added"},"documentsWindowBannerTextColor":{"lightBlue":"added","lightPurple":"added","lightPink":"added","lightRed":"added","lightOrange":"added","lightYellow":"added","lightGreen":"added","lightGraphite":"added","darkBlue":"added","darkPurple":"added","darkPink":"added","darkRed":"added","darkOrange":"added","darkYellow":"added","darkGreen":"added","darkGraphite":"added"},"documentsWindowBannerButtonColor":{"lightBlue":"added","lightPurple":"added","lightPink":"added","lightRed":"added","lightOrange":"added","lightYellow":"added","lightGreen":"added","lightGraphite":"added","darkBlue":"added","darkPurple":"added","darkPink":"added","darkRed":"added","darkOrange":"added","darkYellow":"added","darkGreen":"added","darkGraphite":"added"},"documentsWindowBannerBorderColor":{"lightBlue":"added","lightPurple":"added","lightPink":"added","lightRed":"added","lightOrange":"added","lightYellow":"added","lightGreen":"added","lightGraphite":"added","darkBlue":"added","darkPurple":"added","darkPink":"added","darkRed":"added","darkOrange":"added","darkYellow":"added","darkGreen":"added","darkGraphite":"added"}},"plist":{"documents-window-banner-border":{"light":{"value":"added","interpolation":"added"},"dark":{"value":"added","interpolation":"added"}},"assistant-capsule-yellow":{"dark":{"value":"changed","interpolation":"changed"}},"assistant-capsule-green":{"light":{"value":"changed","interpolation":"changed"}},"documents-window-banner-background":{"light":{"value":"added","interpolation":"added"},"dark":{"value":"added","interpolation":"added"}},"documents-window-banner-text":{"dark":{"value":"added","interpolation":"added"},"light":{"value":"added","interpolation":"added"}},"documents-window-banner-button":{"dark":{"value":"added","interpolation":"added"},"light":{"value":"added","interpolation":"added"}},"assistant-capsule-red":{"dark":{"value":"changed","interpolation":"changed"}}},"counters":{"added":80,"changed":30}},"v67":{"theme":{"assistantCapsuleGreyColor":{"lightBlue":"changed","lightPurple":"changed","lightPink":"changed","lightRed":"changed","lightOrange":"changed","lightYellow":"changed","lightGreen":"changed","lightGraphite":"changed","darkBlue":"changed","darkPurple":"changed","darkPink":"changed","darkRed":"changed","darkOrange":"changed","darkYellow":"changed","darkGreen":"changed","darkGraphite":"changed"}},"plist":{"assistant-capsule-grey":{"light":{"value":"changed","interpolation":"changed"},"dark":{"value":"changed","interpolation":"changed"}}},"counters":{"changed":20}},"v66":{"theme":{"assistantCapsuleRedColor":{"lightBlue":"added","lightPurple":"added","lightPink":"added","lightRed":"added","lightOrange":"added","lightYellow":"added","lightGreen":"added","lightGraphite":"added","darkBlue":"added","darkPurple":"added","darkPink":"added","darkRed":"added","darkOrange":"added","darkYellow":"added","darkGreen":"added","darkGraphite":"added"},"assistantCapsuleYellowColor":{"lightBlue":"added","lightPurple":"added","lightPink":"added","lightRed":"added","lightOrange":"added","lightYellow":"added","lightGreen":"added","lightGraphite":"added","darkBlue":"added","darkPurple":"added","darkPink":"added","darkRed":"added","darkOrange":"added","darkYellow":"added","darkGreen":"added","darkGraphite":"added"},"assistantCapsuleGreyColor":{"lightBlue":"added","lightPurple":"added","lightPink":"added","lightRed":"added","lightOrange":"added","lightYellow":"added","lightGreen":"added","lightGraphite":"added","darkBlue":"added","darkPurple":"added","darkPink":"added","darkRed":"added","darkOrange":"added","darkYellow":"added","darkGreen":"added","darkGraphite":"added"},"assistantCapsuleGreenColor":{"lightBlue":"added","lightPurple":"added","lightPink":"added","lightRed":"added","lightOrange":"added","lightYellow":"added","lightGreen":"added","lightGraphite":"added","darkBlue":"added","darkPurple":"added","darkPink":"added","darkRed":"added","darkOrange":"added","darkYellow":"added","darkGreen":"added","darkGraphite":"added"},"assistantSelectionColor":{"lightBlue":"added","lightPurple":"added","lightPink":"added","lightRed":"added","lightOrange":"added","lightYellow":"added","lightGreen":"added","lightGraphite":"added","darkBlue":"added","darkPurple":"added","darkPink":"added","darkRed":"added","darkOrange":"added","darkYellow":"added","darkGreen":"added","darkGraphite":"added"}},"plist":{"assistant-selection-color":{"light":{"value":"added"}},"assistant-capsule-yellow":{"dark":{"value":"added","interpolation":"added"},"light":{"value":"added","interpolation":"added"}},"assistant-capsule-green":{"light":{"value":"added","interpolation":"added"},"dark":{"value":"added","interpolation":"added"}},"assistant-capsule-grey":{"light":{"value":"added","interpolation":"added"},"dark":{"value":"added","interpolation":"added"}},"assistant-capsule-red":{"light":{"value":"added","interpolation":"added"},"dark":{"value":"added","interpolation":"added"}},"assistant-capsule-disabled":{"dark":{"value":"added","interpolation":"added"},"light":{"value":"added","interpolation":"added"}}},"counters":{"added":101}},"v64":{"plist":{"components-search-result-highlight-underline":{"dark":{"value":"added","interpolation":"added"},"light":{"value":"added","interpolation":"added"}},"components-search-result-highlight-background":{"dark":{"value":"added","interpolation":"added"},"light":{"value":"added","interpolation":"added"}},"components-filter-bar-background":{"light":{"value":"added"},"dark":{"value":"added","interpolation":"added"}},"components-kind-bar-background":{"light":{"value":"added"},"dark":{"value":"added","interpolation":"added"}}},"counters":{"added":14}},"v62":{"theme":{"documentsWindowThumbnailBorderColor":{"darkBlue":"changed","darkPurple":"changed","darkPink":"changed","darkRed":"changed","darkOrange":"changed","darkYellow":"changed","darkGreen":"changed","darkGraphite":"changed"},"documentsWindowStatusIconColor":{"lightBlue":"added","lightPurple":"added","lightPink":"added","lightRed":"added","lightOrange":"added","lightYellow":"added","lightGreen":"added","lightGraphite":"added","darkBlue":"added","darkPurple":"added","darkPink":"added","darkRed":"added","darkOrange":"added","darkYellow":"added","darkGreen":"added","darkGraphite":"added"},"documentsWindowStatusIconColorSelected":{"lightBlue":"added","lightPurple":"added","lightPink":"added","lightRed":"added","lightOrange":"added","lightYellow":"added","lightGreen":"added","lightGraphite":"added","darkBlue":"added","darkPurple":"added","darkPink":"added","darkRed":"added","darkOrange":"added","darkYellow":"added","darkGreen":"added","darkGraphite":"added"}},"plist":{"documents-window-thumbnail-border":{"dark":{"value":"changed","interpolation":"changed"}},"documents-window-vertical-divider":{"light":{"value":"changed","interpolation":"changed"}},"documents-window-status-icon":{"dark":{"value":"added","interpolation":"added"},"light":{"value":"added","interpolation":"added"}},"documents-window-status-icon-selected":{"light":{"value":"added","interpolation":"added"}}},"counters":{"added":38,"changed":12}},"v61":{"theme":{"documentItemOverlayColor":{"lightBlue":"added","lightPurple":"added","lightPink":"added","lightRed":"added","lightOrange":"added","lightYellow":"added","lightGreen":"added","lightGraphite":"added","darkBlue":"added","darkPurple":"added","darkPink":"added","darkRed":"added","darkOrange":"added","darkYellow":"added","darkGreen":"added","darkGraphite":"added"},"componentPaneTextItemMissingFontBackgroundColor":{"lightBlue":"added","lightPurple":"added","lightPink":"added","lightRed":"added","lightOrange":"added","lightYellow":"added","lightGreen":"added","lightGraphite":"added","darkBlue":"added","darkPurple":"added","darkPink":"added","darkRed":"added","darkOrange":"added","darkYellow":"added","darkGreen":"added","darkGraphite":"added"}},"plist":{"document-item-overlay":{"dark":{"value":"added","interpolation":"added"},"light":{"value":"added","interpolation":"added"}},"component-pane-text-item-missing-font-background":{"light":{"value":"added","interpolation":"added"}}},"counters":{"added":38}},"v60.1":{"theme":{"componentPaneGroupPreviewBackgroundColor":{"lightBlue":"added","lightPurple":"added","lightPink":"added","lightRed":"added","lightOrange":"added","lightYellow":"added","lightGreen":"added","lightGraphite":"added","darkBlue":"added","darkPurple":"added","darkPink":"added","darkRed":"added","darkOrange":"added","darkYellow":"added","darkGreen":"added","darkGraphite":"added"}},"plist":{"component-pane-group-preview-background":{"dark":{"value":"added","interpolation":"added"},"light":{"value":"added","interpolation":"added"}}},"counters":{"added":20}},"v60":{"theme":{"documentsWindowSelectionColor":{"lightBlue":"added","lightPurple":"added","lightPink":"added","lightRed":"added","lightOrange":"added","lightYellow":"added","lightGreen":"added","lightGraphite":"added","darkBlue":"added","darkPurple":"added","darkPink":"added","darkRed":"added","darkOrange":"added","darkYellow":"added","darkGreen":"added","darkGraphite":"added"},"documentsWindowUnemphasizedSelectionColor":{"lightBlue":"added","lightPurple":"added","lightPink":"added","lightRed":"added","lightOrange":"added","lightYellow":"added","lightGreen":"added","lightGraphite":"added","darkBlue":"added","darkPurple":"added","darkPink":"added","darkRed":"added","darkOrange":"added","darkYellow":"added","darkGreen":"added","darkGraphite":"added"},"documentsWindowThumbnailBorderColor":{"lightBlue":"added","lightPurple":"added","lightPink":"added","lightRed":"added","lightOrange":"added","lightYellow":"added","lightGreen":"added","lightGraphite":"added","darkBlue":"added","darkPurple":"added","darkPink":"added","darkRed":"added","darkOrange":"added","darkYellow":"added","darkGreen":"added","darkGraphite":"added"},"documentsWindowUnemphasizedThumbnailBorderColor":{"lightBlue":"added","lightPurple":"added","lightPink":"added","lightRed":"added","lightOrange":"added","lightYellow":"added","lightGreen":"added","lightGraphite":"added","darkBlue":"added","darkPurple":"added","darkPink":"added","darkRed":"added","darkOrange":"added","darkYellow":"added","darkGreen":"added","darkGraphite":"added"},"documentsWindowThumbnailBackgroundColor":{"lightBlue":"added","lightPurple":"added","lightPink":"added","lightRed":"added","lightOrange":"added","lightYellow":"added","lightGreen":"added","lightGraphite":"added","darkBlue":"added","darkPurple":"added","darkPink":"added","darkRed":"added","darkOrange":"added","darkYellow":"added","darkGreen":"added","darkGraphite":"added"},"documentsWindowTextSelectionColor":{"lightBlue":"added","lightPurple":"added","lightPink":"added","lightRed":"added","lightOrange":"added","lightYellow":"added","lightGreen":"added","lightGraphite":"added","darkBlue":"added","darkPurple":"added","darkPink":"added","darkRed":"added","darkOrange":"added","darkYellow":"added","darkGreen":"added","darkGraphite":"added"},"documentsWindowUnemphasizedTextSelectionColor":{"lightBlue":"added","lightPurple":"added","lightPink":"added","lightRed":"added","lightOrange":"added","lightYellow":"added","lightGreen":"added","lightGraphite":"added","darkBlue":"added","darkPurple":"added","darkPink":"added","darkRed":"added","darkOrange":"added","darkYellow":"added","darkGreen":"added","darkGraphite":"added"}},"plist":{"documents-window-thumbnail-border":{"light":{"value":"added","interpolation":"added"},"dark":{"value":"added","interpolation":"added"}},"documents-window-vertical-divider":{"dark":{"value":"added","interpolation":"added"},"light":{"value":"added","interpolation":"added"}},"documents-window-thumbnail-bg":{"dark":{"value":"added","interpolation":"added"},"light":{"value":"added","interpolation":"added"}},"preferences-asset-library-header-background":{"light":{"value":"added"}},"documents-window-text-selection":{"light":{"value":"added"}},"documents-window-divider":{"dark":{"value":"added","interpolation":"added"},"light":{"value":"added","interpolation":"added"}},"preferences-asset-library-header-border":{"dark":{"value":"added","interpolation":"added"},"light":{"value":"added","interpolation":"added"}},"documents-window-selection":{"light":{"value":"added"}}},"counters":{"added":135}}}}